Metadata-Version: 1.0
Name: traveltask-google-artifact-registry
Version: 0.0.1
Summary: A Travel Task to download/upload a Python package from/to Google Artifact Registry using Pip
Home-page: UNKNOWN
Author: UNKNOWN
Author-email: UNKNOWN
License: UNKNOWN
Platform: UNKNOWN
